README.md
setup.cfg
setup.py
seam_erasure/__init__.py
seam_erasure/accumulate_coo.py
seam_erasure/bilerp_energy.py
seam_erasure/cli.py
seam_erasure/dirichlet.py
seam_erasure/find_seam.py
seam_erasure/lsq_constraints.py
seam_erasure/mask.py
seam_erasure/obj_reader.py
seam_erasure/points_in_triangle.py
seam_erasure/seam_erasure.py
seam_erasure/seam_gradient.py
seam_erasure/seam_intervals.py
seam_erasure/seam_value_energy_lerp.py
seam_erasure/seam_value_energy_texture.py
seam_erasure/texture.py
seam_erasure/util.py
seam_erasure/weight_data.py
seam_erasure.egg-info/PKG-INFO
seam_erasure.egg-info/SOURCES.txt
seam_erasure.egg-info/dependency_links.txt
seam_erasure.egg-info/entry_points.txt
seam_erasure.egg-info/requires.txt
seam_erasure.egg-info/top_level.txt