Metadata-Version: 2.1
Name: seam-erasure
Version: 1.0.5
Summary: Seamlessly erase seams from your favorite 3D models.
Home-page: https://github.com/zfergus/seam-erasure
Author: Zachary Ferguson
Author-email: zfergus@nyu.edu
License: MIT
Project-URL: Bug Reports, https://github.com/zfergus/seam-erasure/issues
Project-URL: Research Project Page, https://cragl.cs.gmu.edu/seamless/
Project-URL: Paper, https://goo.gl/1LwB3Z
Project-URL: Video, https://youtu.be/kCryf9n82Y8
Project-URL: Source, https://github.com/zfergus/seam-erasure/
Keywords: 3D Modeling,Textures,Computer Graphics
Platform: UNKNOWN
Classifier: Development Status :: 5 - Production/Stable
Classifier: Intended Audience :: End Users/Desktop
Classifier: Intended Audience :: Science/Research
Classifier: Topic :: Multimedia :: Graphics :: 3D Modeling
Classifier: License :: OSI Approved :: MIT License
Classifier: Programming Language :: Python :: 2
Classifier: Programming Language :: Python :: 2.7
Classifier: Programming Language :: Python :: 3
Classifier: Programming Language :: Python :: 3.4
Classifier: Programming Language :: Python :: 3.5
Classifier: Programming Language :: Python :: 3.6
Classifier: Programming Language :: Python :: 3.7
Requires-Python: >= 2.7
Provides-Extra: cholmod
Provides-Extra: web-ui
